openrank/onchainscore/__init__.py
openrank/onchainscore/chainconf.py
openrank/onchainscore/cliutil.py
openrank/onchainscore/util.py
openrank/onchainscore/abi/__init__.py
openrank/onchainscore/abi/v0.json
openrank/onchainscore/abi/v1.json
openrank/onchainscore/cli/__init__.py
openrank/onchainscore/cli/__main__.py
openrank_onchain_score-0.1.0.dist-info/entry_points.txt
openrank_onchain_score-0.1.0.dist-info/WHEEL
openrank_onchain_score-0.1.0.dist-info/METADATA
openrank_onchain_score-0.1.0.dist-info/RECORD
