Metadata-Version: 2.3
Name: openrank-onchain-score
Version: 0.1.0
Summary: A package and CLI tool to manage OpenRank scores onchain.
Author-email: Eugene Kim <ek@karma3labs.com>
Maintainer-email: Eugene Kim <ek@karma3labs.com>
Requires-Python: >=3.10
Classifier: License :: OSI Approved :: MIT License
Requires-Dist: typer~=0.15
Requires-Dist: web3~=7.6
Requires-Dist: structlog~=24.4
Requires-Dist: rich~=13.9
Project-URL: Homepage, https://github.com/openrankprotocol/py-onchain-score
Project-URL: Issues, https://github.com/openrankprotocol/py-onchain-score/issues
Project-URL: Repository, https://github.com/openrankprotocol/py-onchain-score.git
